{"0vix": {"Comptroller": [0, 0, 0, 19, 0, 2, 8, 2, 4, 3, 1, 27, 0, 3, 11, 8]}}
{"balancer": {"Migrations": [0, 0, 0, 0, 0, 0, 0, 0, 0, 0, 0, 0, 0, 0, 0, 1]}}
{"BonqDAO": {"BonqAttacker": [0, 0, 0, 2, 0, 2, 0, 0, 0, 1, 0, 0, 0, 0, 1, 1]}}
{"bZx": {"IUniswapV3PoolActions": [0, 0, 0, 0, 0, 2, 0, 0, 3, 0, 0, 0, 0, 2, 0, 11]}}
{"defrost": {"collateralVault": [0, 0, 1, 3, 0, 0, 0, 0, 1, 0, 0, 1, 0, 0, 0, 3], "vaultEngine": [0, 0, 0, 0, 0, 0, 0, 1, 0, 0, 0, 0, 0, 0, 0, 3], "vaultEngineData": [0, 0, 0, 1, 0, 0, 0, 0, 0, 0, 0, 0, 0, 0, 0, 3], "IDSOracle": [0, 0, 0, 0, 0, 0, 0, 0, 0, 2, 3, 2, 0, 0, 0, 11]}}
{"harvest": {"VaultV2": [0, 0, 1, 1, 0, 1, 0, 1, 12, 0, 1, 6, 0, 2, 3, 3]}}
{"harvest": {"NoopVault": [0, 0, 0, 1, 0, 1, 0, 0, 6, 1, 1, 5, 0, 2, 3, 3]}}
{"julswap": {"BSCswapRouter": [0, 0, 0, 24, 0, 3, 0, 0, 6, 3, 0, 4, 0, 13, 6, 7]}}
{"julswap": {"TransferHelper": [0, 0, 0, 0, 0, 0, 1, 0, 0, 0, 0, 0, 0, 0, 3, 9]}}
{"kashi": {"KashiPair": [0, 0, 0, 0, 0, 0, 0, 0, 0, 0, 0, 0, 0, 0, 0, 1]}}
{"kyber": {"MockWeth": [0, 0, 0, 6, 0, 4, 1, 0, 0, 0, 0, 0, 0, 0, 4, 8]}}
{"kyber": {"PermissionGroups": [0, 0, 0, 4, 0, 0, 0, 0, 0, 2, 0, 0, 0, 0, 2, 1]}}
{"kyber": {"TestBytes32": [0, 0, 0, 1, 0, 0, 0, 2, 0, 0, 0, 0, 0, 0, 0, 2]}}
{"kyber": {"TokenNoDecimals": [0, 0, 0, 7, 0, 1, 2, 0, 2, 4, 0, 0, 0, 2, 2, 8]}}
{"kyber": {"WETH9": [0, 0, 0, 6, 0, 4, 1, 0, 0, 0, 0, 0, 0, 0, 4, 8]}}
{"leetswap": {"LeetSwapV2Pair": [0, 0, 1, 91, 0, 2, 0, 0, 7, 1, 2, 8, 0, 3, 4, 8]}}
{"Popsicle": {"PopsicleStand": [0, 1, 5, 29, 0, 5, 4, 1, 1, 1, 0, 2, 0, 0, 7, 1]}}
{"Popsicle": {"Sorbettiere": [0, 1, 4, 24, 0, 5, 4, 1, 2, 2, 0, 4, 0, 0, 7, 1]}}
{"Rari": {"RariGovernanceTokenDistributor": [4, 0, 0, 7, 0, 1, 0, 1, 1, 0, 1, 2, 0, 1, 0, 1]}}
{"Rari": {"RariGovernanceTokenUniswapDistributor": [3, 0, 0, 4, 0, 1, 0, 0, 0, 0, 0, 0, 0, 0, 0, 1]}}
{"spartanswap": {"utils": [0, 0, 1, 7, 0, 2, 0, 0, 12, 4, 0, 12, 0, 12, 0, 1]}}
{"spartanswap": {"utilsM": [0, 0, 0, 7, 0, 1, 0, 0, 12, 4, 0, 12, 0, 12, 0, 1]}}
{"spartanswap": {"UtilsV2": [0, 0, 0, 2, 0, 3, 0, 0, 17, 0, 0, 19, 0, 12, 0, 1]}}
{"synthetix": {"Synthetix": [0, 0, 0, 0, 0, 3, 0, 0, 0, 1, 0, 1, 0, 0, 2, 1]}}
{"value": {"ValueMasterPool": [4, 0, 0, 9, 0, 3, 0, 2, 2, 4, 0, 7, 0, 0, 2, 3]}}
{"Warp": {"WarpVaultLP": [0, 0, 0, 0, 0, 1, 0, 0, 0, 1, 0, 2, 0, 0, 4, 3]}}
{"Warp": {"WarpControl": [0, 0, 0, 0, 0, 4, 2, 0, 5, 1, 5, 7, 0, 2, 10, 1]}}
{"yearn": {"yDelegatedVault": [0, 0, 0, 1, 0, 1, 0, 1, 1, 0, 5, 7, 0, 6, 6, 1]}}
{"yearn": {"yVault": [0, 0, 0, 0, 0, 1, 1, 0, 0, 0, 1, 3, 0, 1, 2, 3]}}
{"yearn": {"yWETH": [0, 0, 0, 0, 0, 1, 1, 0, 0, 0, 1, 3, 0, 3, 4, 8]}}